term/__init__.py
term/__main__.py
term-2.5.dist-info/LICENSE
term-2.5.dist-info/METADATA
term-2.5.dist-info/WHEEL
term-2.5.dist-info/top_level.txt
term-2.5.dist-info/RECORD
