Metadata-Version: 2.1
Name: term
Version: 2.5
Summary: An enhanced version of the tty module
Home-page: https://github.com/stefanholek/term
Author: Stefan H. Holek
Author-email: stefan@epy.co.at
License: PSF-2.0
Project-URL: Documentation, https://term.readthedocs.io/en/stable/
Keywords: terminal,tty,setraw,setcbreak,opentty,readto,getyx,cursor position,escape sequence,lightmode,darkmode
Classifier: Development Status :: 5 - Production/Stable
Classifier: Intended Audience :: Developers
Classifier: License :: OSI Approved :: Python Software Foundation License
Classifier: Operating System :: MacOS :: MacOS X
Classifier: Operating System :: POSIX
Classifier: Programming Language :: Python
Classifier: Programming Language :: Python :: 2
Classifier: Programming Language :: Python :: 3
Requires-Python: !=3.0.*,!=3.1.*,!=3.2.*,!=3.3.*,>=2.7
License-File: LICENSE
Provides-Extra: docs
Requires-Dist: sphinx (==5.3.0) ; extra == 'docs'
Requires-Dist: sphinx-rtd-theme (==1.0.0) ; extra == 'docs'
Provides-Extra: pylint
Requires-Dist: pylint ; extra == 'pylint'
